[
    {
        "name": "Total",
        "cases": 9259,
        "death": 679,
        "rec": 1905
    }, {
        "name": "Metro Manila",
        "cases": 7286,
        "death": 539,
        "rec": 1515
    }, {
        "name": "CAR",
        "cases": 43,
        "death": 1,
        "rec": 24
    }, {
        "name": "Region 1",
        "cases": 63,
        "death": 12,
        "rec": 23
    }, {
        "name": "Region 2",
        "cases": 34,
        "death": 1,
        "rec": 23
    }, {
        "name": "Region 3",
        "cases": 409,
        "death": 28,
        "rec": 86
    }, {
        "name": "Region 4A",
        "cases": 1323,
        "death": 90,
        "rec": 218
    }, {
        "name": "Region 4B",
        "cases": 34,
        "death": 4,
        "rec": 10
    }, {
        "name": "Region 5",
        "cases": 67,
        "death": 4,
        "rec": 6
    }, {
        "name": "For Verification",
        "cases": 817,
        "death": 17,
        "rec": 22 
    }
]